astma/__init__.py
astma/__main__.py
astmaxx-0.2.0.dist-info/METADATA
astmaxx-0.2.0.dist-info/WHEEL
astmaxx-0.2.0.dist-info/top_level.txt
astmaxx-0.2.0.dist-info/RECORD
